wide_wild_west/__init__.py
wide_wild_west/data.py
wide_wild_west/main.py
once_upon_a_time-0.0.1.dev2.dist-info/LICENSE.txt
once_upon_a_time-0.0.1.dev2.dist-info/METADATA
once_upon_a_time-0.0.1.dev2.dist-info/WHEEL
once_upon_a_time-0.0.1.dev2.dist-info/top_level.txt
once_upon_a_time-0.0.1.dev2.dist-info/RECORD
